dagster_dg_core/__init__.py
dagster_dg_core/check.py
dagster_dg_core/completion.py
dagster_dg_core/component.py
dagster_dg_core/config.py
dagster_dg_core/context.py
dagster_dg_core/env.py
dagster_dg_core/error.py
dagster_dg_core/py.typed
dagster_dg_core/shared_options.py
dagster_dg_core/version.py
dagster_dg_core/utils/__init__.py
dagster_dg_core/utils/check_utils.py
dagster_dg_core/utils/cli.py
dagster_dg_core/utils/filesystem.py
dagster_dg_core/utils/git.py
dagster_dg_core/utils/paths.py
dagster_dg_core/utils/telemetry.py
dagster_dg_core/utils/warnings.py
dagster_dg_core/utils/editor/__init__.py
dagster_dg_core/utils/editor/vscode_extension_package.json
dagster_dg_core/utils/mcp_client/__init__.py
dagster_dg_core/utils/mcp_client/claude_desktop.py
dagster_dg_core-1.12.13.dist-info/licenses/LICENSE
dagster_dg_core-1.12.13.dist-info/METADATA
dagster_dg_core-1.12.13.dist-info/WHEEL
dagster_dg_core-1.12.13.dist-info/top_level.txt
dagster_dg_core-1.12.13.dist-info/RECORD
